keboola_query_service/__init__.py
keboola_query_service/_version.py
keboola_query_service/client.py
keboola_query_service/exceptions.py
keboola_query_service/models.py
keboola_query_service/py.typed
keboola_query_service-0.1.6.dist-info/METADATA
keboola_query_service-0.1.6.dist-info/WHEEL
keboola_query_service-0.1.6.dist-info/RECORD
