Metadata-Version: 2.4
Name: keboola-query-service
Version: 0.1.6
Summary: Python SDK for Keboola Query Service API
Project-URL: Homepage, https://github.com/keboola/query-service-python-sdk
Project-URL: Documentation, https://developers.keboola.com/
Project-URL: Repository, https://github.com/keboola/query-service-python-sdk
Project-URL: Issues, https://github.com/keboola/query-service-python-sdk/issues
Author-email: Keboola <support@keboola.com>
License-Expression: MIT
Keywords: bigquery,data,keboola,query,snowflake,sql
Classifier: Development Status :: 4 - Beta
Classifier: Intended Audience :: Developers
Classifier: License :: OSI Approved :: MIT License
Classifier: Operating System :: OS Independent
Classifier: Programming Language :: Python :: 3
Classifier: Programming Language :: Python :: 3.10
Classifier: Programming Language :: Python :: 3.11
Classifier: Programming Language :: Python :: 3.12
Classifier: Topic :: Database
Classifier: Topic :: Software Development :: Libraries :: Python Modules
Classifier: Typing :: Typed
Requires-Python: >=3.10
Requires-Dist: httpx>=0.25.0
Provides-Extra: dev
Requires-Dist: mypy>=1.0.0; extra == 'dev'
Requires-Dist: pytest-asyncio>=0.21.0; extra == 'dev'
Requires-Dist: pytest-httpx>=0.22.0; extra == 'dev'
Requires-Dist: pytest>=7.0.0; extra == 'dev'
Requires-Dist: ruff>=0.1.0; extra == 'dev'
